tiledwebmaps-0.2.0.dist-info/LICENSE
tiledwebmaps-0.2.0.dist-info/RECORD
tiledwebmaps-0.2.0.dist-info/top_level.txt
tiledwebmaps-0.2.0.dist-info/WHEEL
tiledwebmaps-0.2.0.dist-info/METADATA
tiledwebmaps/presets.py
tiledwebmaps/geo.py
tiledwebmaps/util.py
tiledwebmaps/__init__.py
tiledwebmaps/backend.cpython-38-x86_64-linux-gnu.so
tiledwebmaps/proj_data/nad.lst
tiledwebmaps/proj_data/proj.db
tiledwebmaps/proj_data/ITRF2008
tiledwebmaps/proj_data/nad27
tiledwebmaps/proj_data/projjson.schema.json
tiledwebmaps/proj_data/nad83
tiledwebmaps/proj_data/other.extra
tiledwebmaps/proj_data/ITRF2014
tiledwebmaps/proj_data/proj.ini
tiledwebmaps/proj_data/CH
tiledwebmaps/proj_data/ITRF2000
tiledwebmaps/proj_data/GL27
tiledwebmaps/proj_data/world
tiledwebmaps/proj_data/triangulation.schema.json
tiledwebmaps/proj_data/deformation_model.schema.json
tiledwebmaps.libs/libgssapi_krb5-497db0c6.so.2.2
tiledwebmaps.libs/libquadmath-96973f99.so.0.0.0
tiledwebmaps.libs/libproj-38a33ff2.so.25.9.5.0
tiledwebmaps.libs/libselinux-0922c95c.so.1
tiledwebmaps.libs/libpcre-9513aab5.so.1.2.0
tiledwebmaps.libs/libkeyutils-dfe70bd6.so.1.5
tiledwebmaps.libs/libsqlite3-80ebcf57.so.0.8.6
tiledwebmaps.libs/libcom_err-2abe824b.so.2.1
tiledwebmaps.libs/libk5crypto-b1f99d5c.so.3.1
tiledwebmaps.libs/liblapack-1ad85175.so.3.4.2
tiledwebmaps.libs/libkrb5-fcafa220.so.3.3
tiledwebmaps.libs/libkrb5support-d0bcff84.so.0.1
tiledwebmaps.libs/libssl-cd1d6220.so.1.0.2k
tiledwebmaps.libs/libcrypto-d3570994.so.1.0.2k
tiledwebmaps.libs/libjbig-78348776.so.2.0
tiledwebmaps.libs/libjpeg-43436dd5.so.62.1.0
tiledwebmaps.libs/libtiff-b6eb22fb.so.5.2.0
tiledwebmaps.libs/libgfortran-91cc3cb1.so.3.0.0
tiledwebmaps.libs/libblas-357956a1.so.3.4.2
